neofoodclub/__init__.py
neofoodclub/neofoodclub.abi3.so
neofoodclub/neofoodclub.pyi
neofoodclub/probability_model.py
neofoodclub/py.typed
neofoodclub-1.0.19.dist-info/METADATA
neofoodclub-1.0.19.dist-info/WHEEL
neofoodclub-1.0.19.dist-info/licenses/LICENSE
neofoodclub-1.0.19.dist-info/RECORD
